{
  "releaseGames": [
    {
      "name": "DayZ (PC)",
      "date": "2026-04-08",
      "url": "https://www.xbox.com/es-ES/games/store/dayz/BSR9NLHVF1KL/0001",
      "cover": "https://store-images.s-microsoft.com/image/apps.23097.69886306496288395.9ec42146-6037-4440-b5c7-3a44e5213cc3.0e09163e-a6c4-40f6-9fe1-24a6b4685c64?q=90&w=177&h=265",
      "platforms": [
        "pc"
      ]
    },
    {
      "name": "ENDLESS™ Legend 2 (PC) - [PREMIUM]",
      "date": "2026-04-08",
      "url": "https://www.xbox.com/es-ES/games/store/endless-legend-2-game-preview/9NQNRZG07H94/0010",
      "cover": "https://store-images.s-microsoft.com/image/apps.25896.13770097640131441.872f5e92-1807-4ece-8c29-254a12ec0b60.85c20f52-8b92-4f95-85b2-a43c2869ad2d?q=90&w=177&h=265",
      "platforms": [
        "pc"
      ]
    },
    {
      "name": "FBC: Firebreak - [PREMIUM]",
      "date": "2026-04-08",
      "url": "https://www.xbox.com/es-ES/games/store/fbc-firebreak/9PDCN8Z4HKRN/0010",
      "cover": "https://store-images.s-microsoft.com/image/apps.45469.14156548122363733.4f126492-95e8-406b-9e86-dfd11800657e.4ed60f35-3ca8-40af-9722-2e99a1608f49?q=90&w=177&h=265",
      "platforms": [
        "xbox",
        "pc",
        "cloud"
      ]
    },
    {
      "name": "Planet Coaster 2",
      "date": "2026-04-09",
      "url": "https://www.xbox.com/es-ES/games/store/planet-coaster-2/9PK5WS0HXQKQ/0010",
      "cover": "https://store-images.s-microsoft.com/image/apps.56461.14268784579049883.7baa6b03-b644-46a0-b2d9-71ca584b3862.fd5441ab-2c3c-40b9-b8d9-f2dd75d57f96?q=90&w=177&h=265",
      "platforms": [
        "xbox",
        "pc",
        "cloud"
      ]
    },
    {
      "name": "Tiny Bookshop",
      "date": "2026-04-10",
      "url": "https://www.xbox.com/es-ES/games/store/tiny-bookshop/9ND19JDMBS3R/0010",
      "cover": "https://store-images.s-microsoft.com/image/apps.27843.13557737472275158.70a58551-687d-4de1-a23b-d2133d48842e.193cfa4e-348b-45ec-9363-97d878e7ab89?q=90&w=177&h=265",
      "platforms": [
        "pc",
        "xbox",
        "cloud"
      ]
    },
    {
      "name": "Football Manager 26 Console & PC - [PREMIUM]",
      "date": "2026-04-13",
      "url": "https://www.xbox.com/es-ES/games/store/football-manager-26-console/9NMNZ4CK59DM/0010",
      "cover": "https://store-images.s-microsoft.com/image/apps.63033.13754609462095808.6e939a74-099e-490d-b009-02e7105155bd.6e09f097-e938-4a50-85b4-6e14b4800029?q=90&w=177&h=265",
      "platforms": [
        "pc",
        "xbox",
        "cloud"
      ]
    },
    {
      "name": "Hades II",
      "date": "2026-04-14",
      "url": "https://www.xbox.com/es-ES/games/store/hades-ii/9PCR3Z2MSM4T/0017",
      "cover": "https://store-images.s-microsoft.com/image/apps.16991.14168713998280490.3bef2b54-b349-4934-b798-3138e1ef4c3c.b84aedda-36ac-44cf-a639-3874a4f72a4d?q=90&w=177&h=265",
      "platforms": [
        "xbox",
        "pc",
        "cloud"
      ]
    },
    {
      "name": "REPLACED",
      "date": "2026-04-14",
      "url": "https://www.xbox.com/es-ES/games/store/replaced/9NV3L234VGXD/0010",
      "cover": "https://store-images.s-microsoft.com/image/apps.58338.14406403719631483.bd276ac9-ac6a-4f3c-83e2-24c925976919.b4898e50-c382-48be-87da-eec53ccebeff?q=90&w=177&h=265",
      "platforms": [
        "xbox",
        "pc",
        "cloud"
      ]
    },
    {
      "name": "The Thaumaturge",
      "date": "2026-04-14",
      "url": "https://www.xbox.com/es-ES/games/store/the-thaumaturge/9MZZZCHZ26NK/0010",
      "cover": "https://store-images.s-microsoft.com/image/apps.23276.13864939885830854.7740e640-fe7b-4e1c-b519-69083e646b25.bb5a65d2-3437-4500-823a-2eb3a41e814e?q=90&w=177&h=265",
      "platforms": [
        "xbox",
        "pc",
        "cloud"
      ]
    },
    {
      "name": "The Elder Scrolls IV: Oblivion Remastered - [PREMIUM]",
      "date": "2026-04-16",
      "url": "https://www.xbox.com/es-ES/games/store/the-elder-scrolls-iv-oblivion-remastered/9NQR437K7PQH/0010",
      "cover": "https://store-images.s-microsoft.com/image/apps.54508.13768907753672648.dcd706bb-ce91-4b3f-9525-10b1d4af8423.ad8946cd-a4cb-4ea2-bbf7-a05b1a4f4126?q=90&w=177&h=265",
      "platforms": [
        "pc",
        "xbox",
        "cloud"
      ]
    },
    {
      "name": "NHL 26",
      "date": "2026-04-16",
      "url": "https://www.xbox.com/es-ES/games/store/nhl-26-edicion-estandar-para-xbox-series-xs/9N5KC05F95XM/0010",
      "cover": "https://store-images.s-microsoft.com/image/apps.9361.14036865830677680.e3b49c32-835f-4209-adb5-b25cddfb1586.6616099b-9d55-4f00-98f4-79dda32fd6b6?q=90&w=177&h=265",
      "platforms": [
        "xbox",
        "cloud"
      ]
    },
    {
      "name": "Call of Duty®: Modern Warfare®",
      "date": "2026-04-17",
      "url": "https://www.xbox.com/es-ES/games/store/call-of-duty-modern-warfare/C5DTJ99626K3/0001",
      "cover": "https://store-images.s-microsoft.com/image/apps.50528.67185831113154542.823e899c-d262-40a0-91f6-eee04bdc3713.dd7010c6-9641-4c5a-b8b5-7eb16ddc67ea?q=90&w=177&h=265",
      "platforms": [
        "pc",
        "xbox",
        "cloud"
      ]
    },
    {
      "name": "Little Rocket Lab - [PREMIUM]",
      "date": "2026-04-21",
      "url": "https://www.xbox.com/es-ES/games/store/little-rocket-lab/9N3M5D5ZSW34/0010",
      "cover": "https://store-images.s-microsoft.com/image/apps.32936.14000344005974621.9729934f-27d2-4900-8aa2-53049eb44202.5ca80ddb-fffd-4d9b-9fde-76a41b9f9201?q=90&w=177&h=265",
      "platforms": [
        "pc",
        "xbox",
        "cloud"
      ]
    },
    {
      "name": "SOPA - Relato de la Papa Robada - [PREMIUM]",
      "date": "2026-04-21",
      "url": "https://www.xbox.com/es-ES/games/store/sopa-relato-de-la-papa-robada/9N221ZTFGQB0/0010",
      "cover": "https://store-images.s-microsoft.com/image/apps.45399.13960509830993635.c8e589d4-58bf-48a0-94b9-7be5647c6cf2.3a36e99d-25c5-4a37-8d16-025e9d1a8fde?q=90&w=177&h=265",
      "platforms": [
        "pc",
        "xbox",
        "cloud"
      ]
    },
    {
      "name": "Vampire Crawlers: The Turbo Wildcard from Vampire Survivors",
      "date": "2026-04-21",
      "url": "https://www.xbox.com/es-ES/games/store/vampire-crawlers-the-turbo-wildcard-from-vampire-survivors/9NMPVJ7TCFD0/0010",
      "cover": "https://store-images.s-microsoft.com/image/apps.58093.13753975954973331.f68a6dfe-1345-43d2-9cf7-a4facb1f9857.c7421d49-f1f3-4904-b01e-7a14e4c92e1a?q=90&w=177&h=265",
      "platforms": [
        "xbox",
        "pc",
        "cloud"
      ]
    },
    {
      "name": "Kiln",
      "date": "2026-04-23",
      "url": "https://www.xbox.com/es-ES/games/store/kiln/9MW53ZKZH168/0010",
      "cover": "https://store-images.s-microsoft.com/image/apps.8202.13846114870355423.c6d5bbc2-3a52-4589-8bbf-606749aa483c.212d1263-476d-49c3-972d-3bc343d29dc0?q=90&w=177&h=265",
      "platforms": [
        "xbox",
        "pc"
      ]
    }
  ],
  "leavingGames": [
    {
      "name": "Ashen",
      "date": "2026-04-15",
      "url": "https://www.xbox.com/es-ES/games/store/ashen/BNXLPPCVS0HN/0001",
      "cover": "https://store-images.s-microsoft.com/image/apps.39596.67644652336133489.b3703282-21c5-4da4-9f47-ba53b33b37b5.569189bd-72c6-4e18-bae2-96f3542515b3?q=90&w=177&h=265",
      "platforms": [
        "xbox",
        "pc",
        "cloud"
      ]
    },
    {
      "name": "Eiyuden Chronicle: Hundred Heroes",
      "date": "2026-04-15",
      "url": "https://www.xbox.com/es-ES/games/store/eiyuden-chronicle-hundred-heroes/9N8Z1ZL33LM9/0010",
      "cover": "https://store-images.s-microsoft.com/image/apps.36865.13556919803691894.87ef516e-a908-4d0f-8db2-ac932ea8385c.8d013640-8b04-4a46-a437-b5a3f77bdd2e?q=90&w=177&h=265",
      "platforms": [
        "pc",
        "xbox",
        "cloud"
      ]
    },
    {
      "name": "Grand Theft Auto V",
      "date": "2026-04-15",
      "url": "https://www.xbox.com/es-ES/games/store/grand-theft-auto-v-xbox-series-xs/9NXMBTB02ZSF/0010",
      "cover": "https://store-images.s-microsoft.com/image/apps.25111.14171925115759792.46ff70c5-7760-41a8-9ced-d2de5ae78f17.a595ad6c-5ee2-4d5f-96ed-96c2c62c46e0?q=90&w=177&h=265",
      "platforms": [
        "pc",
        "xbox",
        "cloud"
      ]
    },
    {
      "name": "Little Pony: Misterio en los Altos de Céfiro",
      "date": "2026-04-15",
      "url": "https://www.xbox.com/es-es/games/store/my-little-pony-misterio-en-los-altos-de-céfiro/9pmcmr52j1b5",
      "cover": "https://store-images.s-microsoft.com/image/apps.36671.14300494031996818.c15e6de0-6f08-463f-8420-37eee926402c.80041110-537d-4f61-b8dc-876ca0098829?q=90&w=177&h=265",
      "platforms": [
        "pc",
        "xbox",
        "cloud"
      ]
    },
    {
      "name": "Terra Invicta",
      "date": "2026-04-15",
      "url": "https://www.xbox.com/es-ES/games/store/terra-invicta/9PB0GLGXQZ83/0010",
      "cover": "https://store-images.s-microsoft.com/image/apps.15179.14128659347127760.ef7aff29-92b5-4960-a613-ef7c4fe07abc.620e3cf0-9adc-430e-a962-9c34c540bbaf?q=90&w=177&h=265",
      "platforms": [
        "pc"
      ]
    }
  ],
  "freePlayDays": [
    {
      "name": "Polterguys: Possession Party",
      "date": "2026-02-19",
      "url": "https://www.xbox.com/es-ES/games/store/polterguys-possession-party/9NPQR5GSZV3F/0010",
      "cover": "https://store-images.s-microsoft.com/image/apps.5573.13784155691468416.07d1cd9e-85db-45bd-bcb1-b0fe09dca485.98b3af9e-24b3-42b1-84c1-ce307e46bcb6?q=90&w=177&h=265",
      "platforms": [
        "xbox"
      ],
      "dateLeaving": "2026-02-22"
    },
    {
      "name": "Jujutsu Kaisen Cursed Clash",
      "date": "2026-02-19",
      "url": "https://www.xbox.com/es-ES/games/store/jujutsu-kaisen-cursed-clash/9N1T03Q2J6NH/0010",
      "cover": "https://store-images.s-microsoft.com/image/apps.36584.13965211066101112.5461a737-b473-4ef5-94c7-1976f473c1c1.b0516656-69bd-4b69-85e5-5b68118b6be9?q=90&w=177&h=265",
      "platforms": [
        "xbox"
      ],
      "dateLeaving": "2026-02-22"
    }
  ]
}